crabber/__init__.py
crabber/exceptions.py
crabber/models.py
python_crabber-1.1.1.dist-info/LICENSE
python_crabber-1.1.1.dist-info/WHEEL
python_crabber-1.1.1.dist-info/METADATA
python_crabber-1.1.1.dist-info/RECORD
