Metadata-Version: 2.1
Name: python-crabber
Version: 1.1.1
Summary: A Python client for the Crabber REST API.
Home-page: https://pypi.org/project/python-crabber
License: GPL-2.0-only
Author: Jake Ledoux
Author-email: contactjakeledoux@gmail.com
Requires-Python: >=3.7,<3.11
Classifier: License :: OSI Approved :: GNU General Public License v2 (GPLv2)
Classifier: Programming Language :: Python :: 3
Classifier: Programming Language :: Python :: 3.10
Classifier: Programming Language :: Python :: 3.7
Classifier: Programming Language :: Python :: 3.8
Classifier: Programming Language :: Python :: 3.9
Requires-Dist: requests (>=2.26.0,<3.0.0)
Project-URL: Documentation, https://python-crabber.readthedocs.io/en/latest/
Project-URL: Repository, https://github.com/crabber-net/python-crabber.git
